cpyamf/__init__.py
cpyamf/amf0.pxd
cpyamf/amf3.pxd
cpyamf/codec.pxd
cpyamf/util.pxd
pyamf/__init__.py
pyamf/_version.py
pyamf/alias.py
pyamf/amf0.py
pyamf/amf3.py
pyamf/codec.py
pyamf/python.py
pyamf/sol.py
pyamf/versions.py
pyamf/xml.py
pyamf/adapters/__init__.py
pyamf/adapters/_array.py
pyamf/adapters/_collections.py
pyamf/adapters/_decimal.py
pyamf/adapters/_django_contrib_auth_models.py
pyamf/adapters/_django_db_models_base.py
pyamf/adapters/_django_db_models_fields.py
pyamf/adapters/_django_db_models_query.py
pyamf/adapters/_django_utils_translation.py
pyamf/adapters/_elixir.py
pyamf/adapters/_google_appengine_api_datastore_types.py
pyamf/adapters/_google_appengine_ext_blobstore.py
pyamf/adapters/_google_appengine_ext_db.py
pyamf/adapters/_google_appengine_ext_ndb.py
pyamf/adapters/_sets.py
pyamf/adapters/_sqlalchemy_orm.py
pyamf/adapters/_sqlalchemy_orm_collections.py
pyamf/adapters/_weakref.py
pyamf/adapters/gae_base.py
pyamf/adapters/models.py
pyamf/adapters/util.py
pyamf/adapters/tests/__init__.py
pyamf/adapters/tests/test_array.py
pyamf/adapters/tests/test_collections.py
pyamf/adapters/tests/test_django.py
pyamf/adapters/tests/test_elixir.py
pyamf/adapters/tests/test_sqlalchemy.py
pyamf/adapters/tests/test_weakref.py
pyamf/adapters/tests/django_app/__init__.py
pyamf/adapters/tests/django_app/settings.py
pyamf/adapters/tests/django_app/adapters/__init__.py
pyamf/adapters/tests/django_app/adapters/models.py
pyamf/adapters/tests/google/__init__.py
pyamf/adapters/tests/google/_ndb_models.py
pyamf/adapters/tests/google/_xdb_models.py
pyamf/adapters/tests/google/test_blobstore.py
pyamf/adapters/tests/google/test_datastore_types.py
pyamf/adapters/tests/google/test_ndb.py
pyamf/adapters/tests/google/test_xdb.py
pyamf/flex/__init__.py
pyamf/flex/data.py
pyamf/flex/messaging.py
pyamf/remoting/__init__.py
pyamf/remoting/amf0.py
pyamf/remoting/amf3.py
pyamf/remoting/client/__init__.py
pyamf/remoting/gateway/__init__.py
pyamf/remoting/gateway/django.py
Py3AMF-0.8.12.dist-info/LICENSE.txt
Py3AMF-0.8.12.dist-info/METADATA
Py3AMF-0.8.12.dist-info/WHEEL
Py3AMF-0.8.12.dist-info/top_level.txt
Py3AMF-0.8.12.dist-info/RECORD
