Metadata-Version: 2.1
Name: Py3AMF
Version: 0.8.12
Summary: AMF support for Python
Home-page: https://github.com/StdCarrot/Py3AMF
Author: The Py3AMF Project
Author-email: yhbu@stdc.so
License: MIT License
Keywords: python3 amf amf0 amf3 flex flash remoting rpc http flashplayer air bytearray
Requires-Dist: defusedxml
Provides-Extra: django
Requires-Dist: Django (>=0.96) ; extra == 'django'
Provides-Extra: elixir
Requires-Dist: Elixir (>=0.7.1) ; extra == 'elixir'
Provides-Extra: lxml
Requires-Dist: lxml (>=4.4.0) ; extra == 'lxml'
Provides-Extra: six
Requires-Dist: six (>=1.10.0) ; extra == 'six'
Provides-Extra: sqlalchemy
Requires-Dist: SQLAlchemy (>=0.4) ; extra == 'sqlalchemy'
Provides-Extra: twisted
Requires-Dist: Twisted (>=16.0.0) ; extra == 'twisted'
